MANIFEST.in
setup.py
Plutonium.egg-info/PKG-INFO
Plutonium.egg-info/SOURCES.txt
Plutonium.egg-info/dependency_links.txt
Plutonium.egg-info/requires.txt
Plutonium.egg-info/top_level.txt
bin/plutonium
bin/plutonium_starter
plutonium/__init__.py
plutonium/directories.py
plutonium/alembic/env.py
plutonium/alembic/versions/100f6b705440_initial_database.py
plutonium/example_configs/core.json
plutonium/example_configs/logger.json
plutonium/models/__init__.py
plutonium/models/feed.py
plutonium/models/filter.py
plutonium/models/output.py
plutonium/models/torrent.py
plutonium/modules/__init__.py
plutonium/modules/background_process_handler.py
plutonium/modules/cliargumentstreeparser.py
plutonium/modules/commands.py
plutonium/modules/config.py
plutonium/modules/configure.py
plutonium/modules/fetcher.py
plutonium/modules/logger.py
plutonium/modules/plutonium_class.py
plutonium/modules/plutonium_manager.py
plutonium/modules/timer.py
plutonium/modules/tools.py
plutonium/modules/orm/__init__.py
plutonium/modules/orm/base.py
plutonium/modules/orm/manager.py
plutonium/modules/orm/types.py
plutonium/modules/orm/utils.py
plutonium/plugins/__init__.py
plutonium/plugins/plugin.py
plutonium/plugins/plugin_manager.py