Metadata-Version: 1.0
Name: Plutonium
Version: 1.1.0
Summary: RSS fetcher for bittorrent feeds
Home-page: https://github.com/voidpp/plutonium
Author: Lajos Santa
Author-email: santa.lajos@coldline.hu
License: MIT
Platform: UNKNOWN
